Workbook

Sheet Dashboard
B2: Retail Sales Performance Dashboard
B3: ="Orders from "&TEXT(MIN(Orders!$B$2:$B$1201),"mmm yyyy")&" to "&TEXT(MAX(Orders!$B$2:$B$1201),"mmm yyyy")&" | Revenue = Delivered orders only | Amounts in ₹ lakh (1 L = ₹100,000)" -> Orders from Jan 2024 to Sep 2026 | Revenue = Delivered orders only | Amounts in ₹ lakh (1 L = ₹100,000)
B5: FILTERS ▸ | D5: Year | E5: All | H5: Region | I5: All | L5: Category | M5: All | O5: ◂ pick from the dropdowns
B7: REVENUE | D7: PROFIT | F7: PROFIT MARGIN | H7: ORDERS | J7: AVG ORDER VALUE | L7: UNITS SOLD | N7: RETURN RATE | P7: CANCEL RATE
B8: =Analysis!B11/Analysis!B6 -> 205.57014 | D8: =Analysis!B12/Analysis!B6 -> 35.129245 | F8: =Analysis!B13 -> 0.1708869 | H8: =Analysis!B14 -> 1091 | J8: =Analysis!B15 -> 18842.36 | L8: =Analysis!B16 -> 3215 | N8: =Analysis!B20 -> 0.0625 | P8: =Analysis!B21 -> 0.028333333
B9: delivered orders | D9: revenue – cost | F9: profit ÷ revenue | H9: delivered order lines | J9: revenue ÷ orders | L9: delivered units | N9: of all orders | P9: of all orders
B11: KEY INSIGHTS (update automatically with the filters)
B12: =IF(SUM(Analysis!$B$62:$B$64)=0,"No data for this selection","▪ Top category: "&INDEX(Analysis!$A$62:$A$64,MATCH(MAX(Analysis!$B$62:$B$64),Analysis!$B$62:$B$64,0))&" – ₹"&TEXT(MAX(Analysis!$B$62:$B$64),"0.0")&" L ("&TEXT(MAX(Analysis!$B$62:$B$64)/SUM(Analysis!$B$62:$B$64),"0%")&" of revenue)") -> ▪ Top category: Technology – ₹162.8 L (79% of revenue) | J12: =IF(SUM(Analysis!$B$68:$B$71)=0,"","▪ Top region: "&INDEX(Analysis!$A$68:$A$71,MATCH(MAX(Analysis!$B$68:$B$71),Analysis!$B$68:$B$71,0))&" – ₹"&TEXT(MAX(Analysis!$B$68:$B$71),"0.0")&" L ("&TEXT(MAX(Analysis!$B$68:$B$71)/SUM(Analysis!$B$68:$B$71),"0%")&" of revenue)") -> ▪ Top region: North – ₹86.6 L (42% of revenue)
B13: =IF(SUM(Analysis!$B$75:$B$77)=0,"","▪ Best channel: "&INDEX(Analysis!$A$75:$A$77,MATCH(MAX(Analysis!$B$75:$B$77),Analysis!$B$75:$B$77,0))&" – ₹"&TEXT(MAX(Analysis!$B$75:$B$77),"0.0")&" L ("&TEXT(MAX(Analysis!$B$75:$B$77)/SUM(Analysis!$B$75:$B$77),"0%")&" of revenue)") -> ▪ Best channel: Online – ₹80.4 L (39% of revenue) | J13: =IF(Analysis!$H$87=0,"","▪ Best-selling product: "&Analysis!$G$87&" – ₹"&TEXT(Analysis!$H$87,"0.0")&" L") -> ▪ Best-selling product: Laptop – ₹94.7 L
B14: =IF(SUM(Analysis!$B$62:$B$64)=0,"","▪ Highest-margin category: "&INDEX(Analysis!$A$62:$A$64,MATCH(MAX(Analysis!$D$62:$D$64),Analysis!$D$62:$D$64,0))&" at "&TEXT(MAX(Analysis!$D$62:$D$64),"0.0%")) -> ▪ Highest-margin category: Office Supplies at 36.4% | J14: ="▪ Returned + cancelled orders: ₹"&TEXT(Analysis!$B$22/Analysis!$B$6,"0.0")&" L of sales not realised" -> ▪ Returned + cancelled orders: ₹20.6 L of sales not realised
B16: TRENDS & BREAKDOWNS
B97: Note: breakdown charts ignore their own filter (category chart ignores Category, region chart ignores Region) so comparisons stay visible; the monthly trend ignores the Year filter. Built from the Orders, Customers and Products sheets.

Sheet About
B1: Retail Sales Analysis – Project Overview
B3: Objective | C3: Understand revenue, profitability and fulfilment quality across products, customer segments, regions and channels, and surface where to focus.
B4: Data | C4: Orders (1,200 order lines, Jan 2024 – Sep 2026), Customers (100), Products (15). Linked by customer_id and product_id. No missing values or duplicate order IDs.
B5: Tools | C5: Microsoft Excel: formulas (SUMIFS, COUNTIFS, INDEX/MATCH, LARGE), data validation dropdowns, native charts.
B6: How to use | C6: Open the Dashboard tab and use the Year, Region and Category dropdowns. All KPIs, insights and charts recalculate.
B7: Sheet guide | C7: Dashboard = presentation layer · Analysis = calculation tables · Orders/Customers/Products/Data_Dictionary = source data.
B8: Added columns | C8: Orders columns O–T (teal headers: order_year, order_month, category, region, segment, city) are formulas that look up product and customer attributes. Source columns A–N are unchanged.
B10: Metric definitions
B11: Revenue | C11: Sum of sales_inr for Delivered orders only. Returned and Cancelled orders are excluded because the revenue was not retained.
B12: Profit / margin | C12: Profit = sales_inr – cost_inr (profit_inr); margin = profit ÷ revenue.
B13: Average order value | C13: Revenue ÷ number of delivered order lines.
B14: Return / cancel rate | C14: Returned (or Cancelled) order lines ÷ all order lines in the selected filter.
B15: Sales not realised | C15: sales_inr of Returned + Cancelled orders.
B16: Currency | C16: Indian rupees. Charts and cards show ₹ lakh (1 lakh = ₹100,000).
B18: Assumptions & caveats
B19: Partial year | C19: 2026 data ends 27 Sep 2026, so 2026 totals are not comparable with full years 2024 and 2025.
B20: Order line | C20: Each row in Orders is one order line (one product); order_id is unique per line.
B21: Cost | C21: cost_inr is an estimate of cost of goods sold, as stated in the Data_Dictionary.

Sheet Analysis
A1: Analysis – calculation tables behind the Dashboard
A2: Every figure here is a live formula over the Orders sheet and responds to the Dashboard filters. Blue = input, black = formula.
A3: Year criteria | B3: =IF(Dashboard!$E$5="All",">0",Dashboard!$E$5) -> >0
A4: Region criteria | B4: =IF(Dashboard!$I$5="All","*",Dashboard!$I$5) -> *
A5: Category criteria | B5: =IF(Dashboard!$M$5="All","*",Dashboard!$M$5) -> *
A6: Lakh divisor (₹) | B6: 100000 | C6: 1 lakh = ₹100,000; chart values are shown in ₹ lakh
A7: Revenue status | B7: Delivered | C7: Only Delivered orders count as revenue/profit (Returned & Cancelled are excluded)
A9: KPI block
A10: Metric | B10: Value
A11: Revenue (₹) | B11: =SUMIFS(Orders!$K$2:$K$1201,Orders!$N$2:$N$1201,$B$7,Orders!$O$2:$O$1201,$B$3,Orders!$Q$2:$Q$1201,$B$5,Orders!$R$2:$R$1201,$B$4) -> 20557014
A12: Profit (₹) | B12: =SUMIFS(Orders!$M$2:$M$1201,Orders!$N$2:$N$1201,$B$7,Orders!$O$2:$O$1201,$B$3,Orders!$Q$2:$Q$1201,$B$5,Orders!$R$2:$R$1201,$B$4) -> 3512924.5
A13: Profit margin | B13: =IF(B11=0,0,B12/B11) -> 0.1708869
A14: Delivered orders | B14: =COUNTIFS(Orders!$N$2:$N$1201,$B$7,Orders!$O$2:$O$1201,$B$3,Orders!$Q$2:$Q$1201,$B$5,Orders!$R$2:$R$1201,$B$4) -> 1091
A15: Avg order value (₹) | B15: =IF(B14=0,0,B11/B14) -> 18842.36
A16: Units sold | B16: =SUMIFS(Orders!$H$2:$H$1201,Orders!$N$2:$N$1201,$B$7,Orders!$O$2:$O$1201,$B$3,Orders!$Q$2:$Q$1201,$B$5,Orders!$R$2:$R$1201,$B$4) -> 3215
A17: All orders (any status) | B17: =COUNTIFS(Orders!$O$2:$O$1201,$B$3,Orders!$Q$2:$Q$1201,$B$5,Orders!$R$2:$R$1201,$B$4) -> 1200
A18: Returned orders | B18: =COUNTIFS(Orders!$N$2:$N$1201,"Returned",Orders!$O$2:$O$1201,$B$3,Orders!$Q$2:$Q$1201,$B$5,Orders!$R$2:$R$1201,$B$4) -> 75
A19: Cancelled orders | B19: =COUNTIFS(Orders!$N$2:$N$1201,"Cancelled",Orders!$O$2:$O$1201,$B$3,Orders!$Q$2:$Q$1201,$B$5,Orders!$R$2:$R$1201,$B$4) -> 34
A20: Return rate | B20: =IF(B17=0,0,B18/B17) -> 0.0625
A21: Cancellation rate | B21: =IF(B17=0,0,B19/B17) -> 0.028333333
A22: Sales not realised (₹) | B22: =SUMIFS(Orders!$K$2:$K$1201,Orders!$N$2:$N$1201,"Returned",Orders!$O$2:$O$1201,$B$3,Orders!$Q$2:$Q$1201,$B$5,Orders!$R$2:$R$1201,$B$4)+SUMIFS(Orders!$K$2:$K$1201,Orders!$N$2:$N$1201,"Cancelled",Orders!$O$2:$O$1201,$B$3,Orders!$Q$2:$Q$1201,$B$5,Orders!$R$2:$R$1201,$B$4) -> 2056900
A24: Monthly trend (ignores Year filter; respects Region & Category)
A25: Month | B25: Month start | C25: Revenue (₹ L) | D25: Profit (₹ L)
A26: =TEXT(B26,"mmm-yy") -> Jan-24 | B26: =DATE(2024,1,1) -> 45292 | C26: =SUMIFS(Orders!$K$2:$K$1201,Orders!$N$2:$N$1201,$B$7,Orders!$P$2:$P$1201,$B26,Orders!$Q$2:$Q$1201,$B$5,Orders!$R$2:$R$1201,$B$4)/$B$6 -> 5.191045 | D26: =SUMIFS(Orders!$M$2:$M$1201,Orders!$N$2:$N$1201,$B$7,Orders!$P$2:$P$1201,$B26,Orders!$Q$2:$Q$1201,$B$5,Orders!$R$2:$R$1201,$B$4)/$B$6 -> 0.901545
A27: =TEXT(B27,"mmm-yy") -> Feb-24 | B27: =EDATE(B26,1) -> 45323 | C27: =SUMIFS(Orders!$K$2:$K$1201,Orders!$N$2:$N$1201,$B$7,Orders!$P$2:$P$1201,$B27,Orders!$Q$2:$Q$1201,$B$5,Orders!$R$2:$R$1201,$B$4)/$B$6 -> 5.07922 | D27: =SUMIFS(Orders!$M$2:$M$1201,Orders!$N$2:$N$1201,$B$7,Orders!$P$2:$P$1201,$B27,Orders!$Q$2:$Q$1201,$B$5,Orders!$R$2:$R$1201,$B$4)/$B$6 -> 1.01802
A28: =TEXT(B28,"mmm-yy") -> Mar-24 | B28: =EDATE(B27,1) -> 45352 | C28: =SUMIFS(Orders!$K$2:$K$1201,Orders!$N$2:$N$1201,$B$7,Orders!$P$2:$P$1201,$B28,Orders!$Q$2:$Q$1201,$B$5,Orders!$R$2:$R$1201,$B$4)/$B$6 -> 5.77089 | D28: =SUMIFS(Orders!$M$2:$M$1201,Orders!$N$2:$N$1201,$B$7,Orders!$P$2:$P$1201,$B28,Orders!$Q$2:$Q$1201,$B$5,Orders!$R$2:$R$1201,$B$4)/$B$6 -> 1.06469
A29: =TEXT(B29,"mmm-yy") -> Apr-24 | B29: =EDATE(B28,1) -> 45383 | C29: =SUMIFS(Orders!$K$2:$K$1201,Orders!$N$2:$N$1201,$B$7,Orders!$P$2:$P$1201,$B29,Orders!$Q$2:$Q$1201,$B$5,Orders!$R$2:$R$1201,$B$4)/$B$6 -> 6.294465 | D29: =SUMIFS(Orders!$M$2:$M$1201,Orders!$N$2:$N$1201,$B$7,Orders!$P$2:$P$1201,$B29,Orders!$Q$2:$Q$1201,$B$5,Orders!$R$2:$R$1201,$B$4)/$B$6 -> 1.074865
A30: =TEXT(B30,"mmm-yy") -> May-24 | B30: =EDATE(B29,1) -> 45413 | C30: =SUMIFS(Orders!$K$2:$K$1201,Orders!$N$2:$N$1201,$B$7,Orders!$P$2:$P$1201,$B30,Orders!$Q$2:$Q$1201,$B$5,Orders!$R$2:$R$1201,$B$4)/$B$6 -> 5.98314 | D30: =SUMIFS(Orders!$M$2:$M$1201,Orders!$N$2:$N$1201,$B$7,Orders!$P$2:$P$1201,$B30,Orders!$Q$2:$Q$1201,$B$5,Orders!$R$2:$R$1201,$B$4)/$B$6 -> 0.85124
A31: =TEXT(B31,"mmm-yy") -> Jun-24 | B31: =EDATE(B30,1) -> 45444 | C31: =SUMIFS(Orders!$K$2:$K$1201,Orders!$N$2:$N$1201,$B$7,Orders!$P$2:$P$1201,$B31,Orders!$Q$2:$Q$1201,$B$5,Orders!$R$2:$R$1201,$B$4)/$B$6 -> 7.82287 | D31: =SUMIFS(Orders!$M$2:$M$1201,Orders!$N$2:$N$1201,$B$7,Orders!$P$2:$P$1201,$B31,Orders!$Q$2:$Q$1201,$B$5,Orders!$R$2:$R$1201,$B$4)/$B$6 -> 0.95577
A32: =TEXT(B32,"mmm-yy") -> Jul-24 | B32: =EDATE(B31,1) -> 45474 | C32: =SUMIFS(Orders!$K$2:$K$1201,Orders!$N$2:$N$1201,$B$7,Orders!$P$2:$P$1201,$B32,Orders!$Q$2:$Q$1201,$B$5,Orders!$R$2:$R$1201,$B$4)/$B$6 -> 6.51812 | D32: =SUMIFS(Orders!$M$2:$M$1201,Orders!$N$2:$N$1201,$B$7,Orders!$P$2:$P$1201,$B32,Orders!$Q$2:$Q$1201,$B$5,Orders!$R$2:$R$1201,$B$4)/$B$6 -> 1.16762
A33: =TEXT(B33,"mmm-yy") -> Aug-24 | B33: =EDATE(B32,1) -> 45505 | C33: =SUMIFS(Orders!$K$2:$K$1201,Orders!$N$2:$N$1201,$B$7,Orders!$P$2:$P$1201,$B33,Orders!$Q$2:$Q$1201,$B$5,Orders!$R$2:$R$1201,$B$4)/$B$6 -> 3.706295 | D33: =SUMIFS(Orders!$M$2:$M$1201,Orders!$N$2:$N$1201,$B$7,Orders!$P$2:$P$1201,$B33,Orders!$Q$2:$Q$1201,$B$5,Orders!$R$2:$R$1201,$B$4)/$B$6 -> 0.630695
A34: =TEXT(B34,"mmm-yy") -> Sep-24 | B34: =EDATE(B33,1) -> 45536 | C34: =SUMIFS(Orders!$K$2:$K$1201,Orders!$N$2:$N$1201,$B$7,Orders!$P$2:$P$1201,$B34,Orders!$Q$2:$Q$1201,$B$5,Orders!$R$2:$R$1201,$B$4)/$B$6 -> 4.64395 | D34: =SUMIFS(Orders!$M$2:$M$1201,Orders!$N$2:$N$1201,$B$7,Orders!$P$2:$P$1201,$B34,Orders!$Q$2:$Q$1201,$B$5,Orders!$R$2:$R$1201,$B$4)/$B$6 -> 0.93925
A35: =TEXT(B35,"mmm-yy") -> Oct-24 | B35: =EDATE(B34,1) -> 45566 | C35: =SUMIFS(Orders!$K$2:$K$1201,Orders!$N$2:$N$1201,$B$7,Orders!$P$2:$P$1201,$B35,Orders!$Q$2:$Q$1201,$B$5,Orders!$R$2:$R$1201,$B$4)/$B$6 -> 8.69628 | D35: =SUMIFS(Orders!$M$2:$M$1201,Orders!$N$2:$N$1201,$B$7,Orders!$P$2:$P$1201,$B35,Orders!$Q$2:$Q$1201,$B$5,Orders!$R$2:$R$1201,$B$4)/$B$6 -> 1.22688
A36: =TEXT(B36,"mmm-yy") -> Nov-24 | B36: =EDATE(B35,1) -> 45597 | C36: =SUMIFS(Orders!$K$2:$K$1201,Orders!$N$2:$N$1201,$B$7,Orders!$P$2:$P$1201,$B36,Orders!$Q$2:$Q$1201,$B$5,Orders!$R$2:$R$1201,$B$4)/$B$6 -> 6.74443 | D36: =SUMIFS(Orders!$M$2:$M$1201,Orders!$N$2:$N$1201,$B$7,Orders!$P$2:$P$1201,$B36,Orders!$Q$2:$Q$1201,$B$5,Orders!$R$2:$R$1201,$B$4)/$B$6 -> 1.13163
A37: =TEXT(B37,"mmm-yy") -> Dec-24 | B37: =EDATE(B36,1) -> 45627 | C37: =SUMIFS(Orders!$K$2:$K$1201,Orders!$N$2:$N$1201,$B$7,Orders!$P$2:$P$1201,$B37,Orders!$Q$2:$Q$1201,$B$5,Orders!$R$2:$R$1201,$B$4)/$B$6 -> 2.833175 | D37: =SUMIFS(Orders!$M$2:$M$1201,Orders!$N$2:$N$1201,$B$7,Orders!$P$2:$P$1201,$B37,Orders!$Q$2:$Q$1201,$B$5,Orders!$R$2:$R$1201,$B$4)/$B$6 -> 0.454575
A38: =TEXT(B38,"mmm-yy") -> Jan-25 | B38: =EDATE(B37,1) -> 45658 | C38: =SUMIFS(Orders!$K$2:$K$1201,Orders!$N$2:$N$1201,$B$7,Orders!$P$2:$P$1201,$B38,Orders!$Q$2:$Q$1201,$B$5,Orders!$R$2:$R$1201,$B$4)/$B$6 -> 9.124415 | D38: =SUMIFS(Orders!$M$2:$M$1201,Orders!$N$2:$N$1201,$B$7,Orders!$P$2:$P$1201,$B38,Orders!$Q$2:$Q$1201,$B$5,Orders!$R$2:$R$1201,$B$4)/$B$6 -> 1.149715
... A58: =TEXT(B58,"mmm-yy") -> Sep-26 | B58: =EDATE(B57,1) -> 46266 | C58: =SUMIFS(Orders!$K$2:$K$1201,Orders!$N$2:$N$1201,$B$7,Orders!$P$2:$P$1201,$B58,Orders!$Q$2:$Q$1201,$B$5,Orders!$R$2:$R$1201,$B$4)/$B$6 -> 3.95573 | D58: =SUMIFS(Orders!$M$2:$M$1201,Orders!$N$2:$N$1201,$B$7,Orders!$P$2:$P$1201,$B58,Orders!$Q$2:$Q$1201,$B$5,Orders!$R$2:$R$1201,$B$4)/$B$6 -> 0.64323
A60: Revenue by category (ignores Category filter)
A61: Label | B61: Revenue (₹ L) | C61: Profit (₹ L) | D61: Margin
A62: Technology | B62: =SUMIFS(Orders!$K$2:$K$1201,Orders!$N$2:$N$1201,$B$7,Orders!$O$2:$O$1201,$B$3,Orders!$R$2:$R$1201,$B$4,Orders!$Q$2:$Q$1201,$A62)/$B$6 -> 162.8168 | C62: =SUMIFS(Orders!$M$2:$M$1201,Orders!$N$2:$N$1201,$B$7,Orders!$O$2:$O$1201,$B$3,Orders!$R$2:$R$1201,$B$4,Orders!$Q$2:$Q$1201,$A62)/$B$6 -> 24.8034 | D62: =IF(B62=0,0,C62/B62) -> 0.15233932
A63: Furniture | B63: =SUMIFS(Orders!$K$2:$K$1201,Orders!$N$2:$N$1201,$B$7,Orders!$O$2:$O$1201,$B$3,Orders!$R$2:$R$1201,$B$4,Orders!$Q$2:$Q$1201,$A63)/$B$6 -> 39.89765 | C63: =SUMIFS(Orders!$M$2:$M$1201,Orders!$N$2:$N$1201,$B$7,Orders!$O$2:$O$1201,$B$3,Orders!$R$2:$R$1201,$B$4,Orders!$Q$2:$Q$1201,$A63)/$B$6 -> 9.28565 | D63: =IF(B63=0,0,C63/B63) -> 0.23273677
A64: Office Supplies | B64: =SUMIFS(Orders!$K$2:$K$1201,Orders!$N$2:$N$1201,$B$7,Orders!$O$2:$O$1201,$B$3,Orders!$R$2:$R$1201,$B$4,Orders!$Q$2:$Q$1201,$A64)/$B$6 -> 2.855695 | C64: =SUMIFS(Orders!$M$2:$M$1201,Orders!$N$2:$N$1201,$B$7,Orders!$O$2:$O$1201,$B$3,Orders!$R$2:$R$1201,$B$4,Orders!$Q$2:$Q$1201,$A64)/$B$6 -> 1.040195 | D64: =IF(B64=0,0,C64/B64) -> 0.36425284
A66: Revenue by region (ignores Region filter)
A67: Label | B67: Revenue (₹ L) | C67: Profit (₹ L) | D67: Margin
A68: North | B68: =SUMIFS(Orders!$K$2:$K$1201,Orders!$N$2:$N$1201,$B$7,Orders!$O$2:$O$1201,$B$3,Orders!$Q$2:$Q$1201,$B$5,Orders!$R$2:$R$1201,$A68)/$B$6 -> 86.62462 | C68: =SUMIFS(Orders!$M$2:$M$1201,Orders!$N$2:$N$1201,$B$7,Orders!$O$2:$O$1201,$B$3,Orders!$Q$2:$Q$1201,$B$5,Orders!$R$2:$R$1201,$A68)/$B$6 -> 15.01932 | D68: =IF(B68=0,0,C68/B68) -> 0.17338396
A69: South | B69: =SUMIFS(Orders!$K$2:$K$1201,Orders!$N$2:$N$1201,$B$7,Orders!$O$2:$O$1201,$B$3,Orders!$Q$2:$Q$1201,$B$5,Orders!$R$2:$R$1201,$A69)/$B$6 -> 23.054795 | C69: =SUMIFS(Orders!$M$2:$M$1201,Orders!$N$2:$N$1201,$B$7,Orders!$O$2:$O$1201,$B$3,Orders!$Q$2:$Q$1201,$B$5,Orders!$R$2:$R$1201,$A69)/$B$6 -> 4.264495 | D69: =IF(B69=0,0,C69/B69) -> 0.18497215
A70: East | B70: =SUMIFS(Orders!$K$2:$K$1201,Orders!$N$2:$N$1201,$B$7,Orders!$O$2:$O$1201,$B$3,Orders!$Q$2:$Q$1201,$B$5,Orders!$R$2:$R$1201,$A70)/$B$6 -> 36.95137 | C70: =SUMIFS(Orders!$M$2:$M$1201,Orders!$N$2:$N$1201,$B$7,Orders!$O$2:$O$1201,$B$3,Orders!$Q$2:$Q$1201,$B$5,Orders!$R$2:$R$1201,$A70)/$B$6 -> 6.47107 | D70: =IF(B70=0,0,C70/B70) -> 0.17512395
A71: West | B71: =SUMIFS(Orders!$K$2:$K$1201,Orders!$N$2:$N$1201,$B$7,Orders!$O$2:$O$1201,$B$3,Orders!$Q$2:$Q$1201,$B$5,Orders!$R$2:$R$1201,$A71)/$B$6 -> 58.93936 | C71: =SUMIFS(Orders!$M$2:$M$1201,Orders!$N$2:$N$1201,$B$7,Orders!$O$2:$O$1201,$B$3,Orders!$Q$2:$Q$1201,$B$5,Orders!$R$2:$R$1201,$A71)/$B$6 -> 9.37436 | D71: =IF(B71=0,0,C71/B71) -> 0.15905093
A73: Revenue by sales channel
A74: Label | B74: Revenue (₹ L) | C74: Profit (₹ L) | D74: Margin
A75: Online | B75: =SUMIFS(Orders!$K$2:$K$1201,Orders!$N$2:$N$1201,$B$7,Orders!$O$2:$O$1201,$B$3,Orders!$Q$2:$Q$1201,$B$5,Orders!$R$2:$R$1201,$B$4,Orders!$F$2:$F$1201,$A75)/$B$6 -> 80.395235 | C75: =SUMIFS(Orders!$M$2:$M$1201,Orders!$N$2:$N$1201,$B$7,Orders!$O$2:$O$1201,$B$3,Orders!$Q$2:$Q$1201,$B$5,Orders!$R$2:$R$1201,$B$4,Orders!$F$2:$F$1201,$A75)/$B$6 -> 12.826635 | D75: =IF(B75=0,0,C75/B75) -> 0.15954472
A76: Store | B76: =SUMIFS(Orders!$K$2:$K$1201,Orders!$N$2:$N$1201,$B$7,Orders!$O$2:$O$1201,$B$3,Orders!$Q$2:$Q$1201,$B$5,Orders!$R$2:$R$1201,$B$4,Orders!$F$2:$F$1201,$A76)/$B$6 -> 68.177755 | C76: =SUMIFS(Orders!$M$2:$M$1201,Orders!$N$2:$N$1201,$B$7,Orders!$O$2:$O$1201,$B$3,Orders!$Q$2:$Q$1201,$B$5,Orders!$R$2:$R$1201,$B$4,Orders!$F$2:$F$1201,$A76)/$B$6 -> 12.247555 | D76: =IF(B76=0,0,C76/B76) -> 0.17964151
A77: Phone | B77: =SUMIFS(Orders!$K$2:$K$1201,Orders!$N$2:$N$1201,$B$7,Orders!$O$2:$O$1201,$B$3,Orders!$Q$2:$Q$1201,$B$5,Orders!$R$2:$R$1201,$B$4,Orders!$F$2:$F$1201,$A77)/$B$6 -> 56.997155 | C77: =SUMIFS(Orders!$M$2:$M$1201,Orders!$N$2:$N$1201,$B$7,Orders!$O$2:$O$1201,$B$3,Orders!$Q$2:$Q$1201,$B$5,Orders!$R$2:$R$1201,$B$4,Orders!$F$2:$F$1201,$A77)/$B$6 -> 10.055055 | D77: =IF(B77=0,0,C77/B77) -> 0.17641328
A79: Revenue by customer segment
A80: Label | B80: Revenue (₹ L) | C80: Profit (₹ L) | D80: Margin
A81: Consumer | B81: =SUMIFS(Orders!$K$2:$K$1201,Orders!$N$2:$N$1201,$B$7,Orders!$O$2:$O$1201,$B$3,Orders!$Q$2:$Q$1201,$B$5,Orders!$R$2:$R$1201,$B$4,Orders!$S$2:$S$1201,$A81)/$B$6 -> 90.025355 | C81: =SUMIFS(Orders!$M$2:$M$1201,Orders!$N$2:$N$1201,$B$7,Orders!$O$2:$O$1201,$B$3,Orders!$Q$2:$Q$1201,$B$5,Orders!$R$2:$R$1201,$B$4,Orders!$S$2:$S$1201,$A81)/$B$6 -> 15.307055 | D81: =IF(B81=0,0,C81/B81) -> 0.17003049
A82: Small Business | B82: =SUMIFS(Orders!$K$2:$K$1201,Orders!$N$2:$N$1201,$B$7,Orders!$O$2:$O$1201,$B$3,Orders!$Q$2:$Q$1201,$B$5,Orders!$R$2:$R$1201,$B$4,Orders!$S$2:$S$1201,$A82)/$B$6 -> 66.126565 | C82: =SUMIFS(Orders!$M$2:$M$1201,Orders!$N$2:$N$1201,$B$7,Orders!$O$2:$O$1201,$B$3,Orders!$Q$2:$Q$1201,$B$5,Orders!$R$2:$R$1201,$B$4,Orders!$S$2:$S$1201,$A82)/$B$6 -> 11.393065 | D82: =IF(B82=0,0,C82/B82) -> 0.1722918
A83: Corporate | B83: =SUMIFS(Orders!$K$2:$K$1201,Orders!$N$2:$N$1201,$B$7,Orders!$O$2:$O$1201,$B$3,Orders!$Q$2:$Q$1201,$B$5,Orders!$R$2:$R$1201,$B$4,Orders!$S$2:$S$1201,$A83)/$B$6 -> 49.418225 | C83: =SUMIFS(Orders!$M$2:$M$1201,Orders!$N$2:$N$1201,$B$7,Orders!$O$2:$O$1201,$B$3,Orders!$Q$2:$Q$1201,$B$5,Orders!$R$2:$R$1201,$B$4,Orders!$S$2:$S$1201,$A83)/$B$6 -> 8.429125 | D83: =IF(B83=0,0,C83/B83) -> 0.17056713
A85: Revenue by product (all 15) and Top 10 ranking
A86: Product ID | B86: Product | C86: Revenue (₹ L) | D86: Rank key | F86: Rank | G86: Top product | H86: Revenue (₹ L)
A87: P001 | B87: =INDEX(Products!$B$2:$B$16,MATCH(A87,Products!$A$2:$A$16,0)) -> Laptop | C87: =SUMIFS(Orders!$K$2:$K$1201,Orders!$N$2:$N$1201,$B$7,Orders!$O$2:$O$1201,$B$3,Orders!$Q$2:$Q$1201,$B$5,Orders!$R$2:$R$1201,$B$4,Orders!$E$2:$E$1201,$A87)/$B$6 -> 94.68 | D87: =C87+ROW()/1000000 -> 94.680087 | F87: 1 | G87: =IF(H87=0,"–",INDEX($B$87:$B$101,MATCH(LARGE($D$87:$D$101,F87),$D$87:$D$101,0))) -> Laptop | H87: =IF(INDEX($C$87:$C$101,MATCH(LARGE($D$87:$D$101,F87),$D$87:$D$101,0))<=0,0,INDEX($C$87:$C$101,MATCH(LARGE($D$87:$D$101,F87),$D$87:$D$101,0))) -> 94.68
A88: P002 | B88: =INDEX(Products!$B$2:$B$16,MATCH(A88,Products!$A$2:$A$16,0)) -> Wireless Mouse | C88: =SUMIFS(Orders!$K$2:$K$1201,Orders!$N$2:$N$1201,$B$7,Orders!$O$2:$O$1201,$B$3,Orders!$Q$2:$Q$1201,$B$5,Orders!$R$2:$R$1201,$B$4,Orders!$E$2:$E$1201,$A88)/$B$6 -> 1.1264 | D88: =C88+ROW()/1000000 -> 1.126488 | F88: 2 | G88: =IF(H88=0,"–",INDEX($B$87:$B$101,MATCH(LARGE($D$87:$D$101,F88),$D$87:$D$101,0))) -> Tablet | H88: =IF(INDEX($C$87:$C$101,MATCH(LARGE($D$87:$D$101,F88),$D$87:$D$101,0))<=0,0,INDEX($C$87:$C$101,MATCH(LARGE($D$87:$D$101,F88),$D$87:$D$101,0))) -> 30.411
A89: P003 | B89: =INDEX(Products!$B$2:$B$16,MATCH(A89,Products!$A$2:$A$16,0)) -> Keyboard | C89: =SUMIFS(Orders!$K$2:$K$1201,Orders!$N$2:$N$1201,$B$7,Orders!$O$2:$O$1201,$B$3,Orders!$Q$2:$Q$1201,$B$5,Orders!$R$2:$R$1201,$B$4,Orders!$E$2:$E$1201,$A89)/$B$6 -> 2.7465 | D89: =C89+ROW()/1000000 -> 2.746589 | F89: 3 | G89: =IF(H89=0,"–",INDEX($B$87:$B$101,MATCH(LARGE($D$87:$D$101,F89),$D$87:$D$101,0))) -> Monitor | H89: =IF(INDEX($C$87:$C$101,MATCH(LARGE($D$87:$D$101,F89),$D$87:$D$101,0))<=0,0,INDEX($C$87:$C$101,MATCH(LARGE($D$87:$D$101,F89),$D$87:$D$101,0))) -> 21.414
A90: P004 | B90: =INDEX(Products!$B$2:$B$16,MATCH(A90,Products!$A$2:$A$16,0)) -> Monitor | C90: =SUMIFS(Orders!$K$2:$K$1201,Orders!$N$2:$N$1201,$B$7,Orders!$O$2:$O$1201,$B$3,Orders!$Q$2:$Q$1201,$B$5,Orders!$R$2:$R$1201,$B$4,Orders!$E$2:$E$1201,$A90)/$B$6 -> 21.414 | D90: =C90+ROW()/1000000 -> 21.41409 | F90: 4 | G90: =IF(H90=0,"–",INDEX($B$87:$B$101,MATCH(LARGE($D$87:$D$101,F90),$D$87:$D$101,0))) -> Office Desk | H90: =IF(INDEX($C$87:$C$101,MATCH(LARGE($D$87:$D$101,F90),$D$87:$D$101,0))<=0,0,INDEX($C$87:$C$101,MATCH(LARGE($D$87:$D$101,F90),$D$87:$D$101,0))) -> 16.875
A91: P005 | B91: =INDEX(Products!$B$2:$B$16,MATCH(A91,Products!$A$2:$A$16,0)) -> Office Chair | C91: =SUMIFS(Orders!$K$2:$K$1201,Orders!$N$2:$N$1201,$B$7,Orders!$O$2:$O$1201,$B$3,Orders!$Q$2:$Q$1201,$B$5,Orders!$R$2:$R$1201,$B$4,Orders!$E$2:$E$1201,$A91)/$B$6 -> 11.4075 | D91: =C91+ROW()/1000000 -> 11.407591 | F91: 5 | G91: =IF(H91=0,"–",INDEX($B$87:$B$101,MATCH(LARGE($D$87:$D$101,F91),$D$87:$D$101,0))) -> Office Chair | H91: =IF(INDEX($C$87:$C$101,MATCH(LARGE($D$87:$D$101,F91),$D$87:$D$101,0))<=0,0,INDEX($C$87:$C$101,MATCH(LARGE($D$87:$D$101,F91),$D$87:$D$101,0))) -> 11.4075
A92: P006 | B92: =INDEX(Products!$B$2:$B$16,MATCH(A92,Products!$A$2:$A$16,0)) -> Office Desk | C92: =SUMIFS(Orders!$K$2:$K$1201,Orders!$N$2:$N$1201,$B$7,Orders!$O$2:$O$1201,$B$3,Orders!$Q$2:$Q$1201,$B$5,Orders!$R$2:$R$1201,$B$4,Orders!$E$2:$E$1201,$A92)/$B$6 -> 16.875 | D92: =C92+ROW()/1000000 -> 16.875092 | F92: 6 | G92: =IF(H92=0,"–",INDEX($B$87:$B$101,MATCH(LARGE($D$87:$D$101,F92),$D$87:$D$101,0))) -> Bookshelf | H92: =IF(INDEX($C$87:$C$101,MATCH(LARGE($D$87:$D$101,F92),$D$87:$D$101,0))<=0,0,INDEX($C$87:$C$101,MATCH(LARGE($D$87:$D$101,F92),$D$87:$D$101,0))) -> 9.63875
A93: P007 | B93: =INDEX(Products!$B$2:$B$16,MATCH(A93,Products!$A$2:$A$16,0)) -> Notebook Pack | C93: =SUMIFS(Orders!$K$2:$K$1201,Orders!$N$2:$N$1201,$B$7,Orders!$O$2:$O$1201,$B$3,Orders!$Q$2:$Q$1201,$B$5,Orders!$R$2:$R$1201,$B$4,Orders!$E$2:$E$1201,$A93)/$B$6 -> 0.451125 | D93: =C93+ROW()/1000000 -> 0.451218 | F93: 7 | G93: =IF(H93=0,"–",INDEX($B$87:$B$101,MATCH(LARGE($D$87:$D$101,F93),$D$87:$D$101,0))) -> Webcam | H93: =IF(INDEX($C$87:$C$101,MATCH(LARGE($D$87:$D$101,F93),$D$87:$D$101,0))<=0,0,INDEX($C$87:$C$101,MATCH(LARGE($D$87:$D$101,F93),$D$87:$D$101,0))) -> 6.8685
A94: P008 | B94: =INDEX(Products!$B$2:$B$16,MATCH(A94,Products!$A$2:$A$16,0)) -> Printer Paper | C94: =SUMIFS(Orders!$K$2:$K$1201,Orders!$N$2:$N$1201,$B$7,Orders!$O$2:$O$1201,$B$3,Orders!$Q$2:$Q$1201,$B$5,Orders!$R$2:$R$1201,$B$4,Orders!$E$2:$E$1201,$A94)/$B$6 -> 0.9592 | D94: =C94+ROW()/1000000 -> 0.959294 | F94: 8 | G94: =IF(H94=0,"–",INDEX($B$87:$B$101,MATCH(LARGE($D$87:$D$101,F94),$D$87:$D$101,0))) -> Headphones | H94: =IF(INDEX($C$87:$C$101,MATCH(LARGE($D$87:$D$101,F94),$D$87:$D$101,0))<=0,0,INDEX($C$87:$C$101,MATCH(LARGE($D$87:$D$101,F94),$D$87:$D$101,0))) -> 5.5704
A95: P009 | B95: =INDEX(Products!$B$2:$B$16,MATCH(A95,Products!$A$2:$A$16,0)) -> Pen Set | C95: =SUMIFS(Orders!$K$2:$K$1201,Orders!$N$2:$N$1201,$B$7,Orders!$O$2:$O$1201,$B$3,Orders!$Q$2:$Q$1201,$B$5,Orders!$R$2:$R$1201,$B$4,Orders!$E$2:$E$1201,$A95)/$B$6 -> 0.36387 | D95: =C95+ROW()/1000000 -> 0.363965 | F95: 9 | G95: =IF(H95=0,"–",INDEX($B$87:$B$101,MATCH(LARGE($D$87:$D$101,F95),$D$87:$D$101,0))) -> Keyboard | H95: =IF(INDEX($C$87:$C$101,MATCH(LARGE($D$87:$D$101,F95),$D$87:$D$101,0))<=0,0,INDEX($C$87:$C$101,MATCH(LARGE($D$87:$D$101,F95),$D$87:$D$101,0))) -> 2.7465
A96: P010 | B96: =INDEX(Products!$B$2:$B$16,MATCH(A96,Products!$A$2:$A$16,0)) -> Bookshelf | C96: =SUMIFS(Orders!$K$2:$K$1201,Orders!$N$2:$N$1201,$B$7,Orders!$O$2:$O$1201,$B$3,Orders!$Q$2:$Q$1201,$B$5,Orders!$R$2:$R$1201,$B$4,Orders!$E$2:$E$1201,$A96)/$B$6 -> 9.63875 | D96: =C96+ROW()/1000000 -> 9.638846 | F96: 10 | G96: =IF(H96=0,"–",INDEX($B$87:$B$101,MATCH(LARGE($D$87:$D$101,F96),$D$87:$D$101,0))) -> Desk Lamp | H96: =IF(INDEX($C$87:$C$101,MATCH(LARGE($D$87:$D$101,F96),$D$87:$D$101,0))<=0,0,INDEX($C$87:$C$101,MATCH(LARGE($D$87:$D$101,F96),$D$87:$D$101,0))) -> 1.9764
A97: P011 | B97: =INDEX(Products!$B$2:$B$16,MATCH(A97,Products!$A$2:$A$16,0)) -> Headphones | C97: =SUMIFS(Orders!$K$2:$K$1201,Orders!$N$2:$N$1201,$B$7,Orders!$O$2:$O$1201,$B$3,Orders!$Q$2:$Q$1201,$B$5,Orders!$R$2:$R$1201,$B$4,Orders!$E$2:$E$1201,$A97)/$B$6 -> 5.5704 | D97: =C97+ROW()/1000000 -> 5.570497
A98: P012 | B98: =INDEX(Products!$B$2:$B$16,MATCH(A98,Products!$A$2:$A$16,0)) -> Webcam | C98: =SUMIFS(Orders!$K$2:$K$1201,Orders!$N$2:$N$1201,$B$7,Orders!$O$2:$O$1201,$B$3,Orders!$Q$2:$Q$1201,$B$5,Orders!$R$2:$R$1201,$B$4,Orders!$E$2:$E$1201,$A98)/$B$6 -> 6.8685 | D98: =C98+ROW()/1000000 -> 6.868598
A99: P013 | B99: =INDEX(Products!$B$2:$B$16,MATCH(A99,Products!$A$2:$A$16,0)) -> Storage Box | C99: =SUMIFS(Orders!$K$2:$K$1201,Orders!$N$2:$N$1201,$B$7,Orders!$O$2:$O$1201,$B$3,Orders!$Q$2:$Q$1201,$B$5,Orders!$R$2:$R$1201,$B$4,Orders!$E$2:$E$1201,$A99)/$B$6 -> 1.0815 | D99: =C99+ROW()/1000000 -> 1.081599
A100: P014 | B100: =INDEX(Products!$B$2:$B$16,MATCH(A100,Products!$A$2:$A$16,0)) -> Desk Lamp | C100: =SUMIFS(Orders!$K$2:$K$1201,Orders!$N$2:$N$1201,$B$7,Orders!$O$2:$O$1201,$B$3,Orders!$Q$2:$Q$1201,$B$5,Orders!$R$2:$R$1201,$B$4,Orders!$E$2:$E$1201,$A100)/$B$6 -> 1.9764 | D100: =C100+ROW()/1000000 -> 1.9765
A101: P015 | B101: =INDEX(Products!$B$2:$B$16,MATCH(A101,Products!$A$2:$A$16,0)) -> Tablet | C101: =SUMIFS(Orders!$K$2:$K$1201,Orders!$N$2:$N$1201,$B$7,Orders!$O$2:$O$1201,$B$3,Orders!$Q$2:$Q$1201,$B$5,Orders!$R$2:$R$1201,$B$4,Orders!$E$2:$E$1201,$A101)/$B$6 -> 30.411 | D101: =C101+ROW()/1000000 -> 30.411101
A103: Revenue by city (all) and Top 8 ranking
A104: City | B104: Revenue (₹ L) | C104: Rank key | F104: Rank | G104: Top city | H104: Revenue (₹ L)
A105: Ahmedabad | B105: =SUMIFS(Orders!$K$2:$K$1201,Orders!$N$2:$N$1201,$B$7,Orders!$O$2:$O$1201,$B$3,Orders!$Q$2:$Q$1201,$B$5,Orders!$R$2:$R$1201,$B$4,Orders!$T$2:$T$1201,$A105)/$B$6 -> 22.37099 | C105: =B105+ROW()/1000000 -> 22.371095 | F105: 1 | G105: =IF(H105=0,"–",INDEX($A$105:$A$116,MATCH(LARGE($C$105:$C$116,F105),$C$105:$C$116,0))) -> Jaipur | H105: =IF(INDEX($B$105:$B$116,MATCH(LARGE($C$105:$C$116,F105),$C$105:$C$116,0))<=0,0,INDEX($B$105:$B$116,MATCH(LARGE($C$105:$C$116,F105),$C$105:$C$116,0))) -> 30.57814
A106: Bengaluru | B106: =SUMIFS(Orders!$K$2:$K$1201,Orders!$N$2:$N$1201,$B$7,Orders!$O$2:$O$1201,$B$3,Orders!$Q$2:$Q$1201,$B$5,Orders!$R$2:$R$1201,$B$4,Orders!$T$2:$T$1201,$A106)/$B$6 -> 10.27606 | C106: =B106+ROW()/1000000 -> 10.276166 | F106: 2 | G106: =IF(H106=0,"–",INDEX($A$105:$A$116,MATCH(LARGE($C$105:$C$116,F106),$C$105:$C$116,0))) -> Gurugram | H106: =IF(INDEX($B$105:$B$116,MATCH(LARGE($C$105:$C$116,F106),$C$105:$C$116,0))<=0,0,INDEX($B$105:$B$116,MATCH(LARGE($C$105:$C$116,F106),$C$105:$C$116,0))) -> 24.911685
A107: Bhubaneswar | B107: =SUMIFS(Orders!$K$2:$K$1201,Orders!$N$2:$N$1201,$B$7,Orders!$O$2:$O$1201,$B$3,Orders!$Q$2:$Q$1201,$B$5,Orders!$R$2:$R$1201,$B$4,Orders!$T$2:$T$1201,$A107)/$B$6 -> 19.941025 | C107: =B107+ROW()/1000000 -> 19.941132 | F107: 3 | G107: =IF(H107=0,"–",INDEX($A$105:$A$116,MATCH(LARGE($C$105:$C$116,F107),$C$105:$C$116,0))) -> Ahmedabad | H107: =IF(INDEX($B$105:$B$116,MATCH(LARGE($C$105:$C$116,F107),$C$105:$C$116,0))<=0,0,INDEX($B$105:$B$116,MATCH(LARGE($C$105:$C$116,F107),$C$105:$C$116,0))) -> 22.37099
A108: Chennai | B108: =SUMIFS(Orders!$K$2:$K$1201,Orders!$N$2:$N$1201,$B$7,Orders!$O$2:$O$1201,$B$3,Orders!$Q$2:$Q$1201,$B$5,Orders!$R$2:$R$1201,$B$4,Orders!$T$2:$T$1201,$A108)/$B$6 -> 7.00611 | C108: =B108+ROW()/1000000 -> 7.006218 | F108: 4 | G108: =IF(H108=0,"–",INDEX($A$105:$A$116,MATCH(LARGE($C$105:$C$116,F108),$C$105:$C$116,0))) -> Pune | H108: =IF(INDEX($B$105:$B$116,MATCH(LARGE($C$105:$C$116,F108),$C$105:$C$116,0))<=0,0,INDEX($B$105:$B$116,MATCH(LARGE($C$105:$C$116,F108),$C$105:$C$116,0))) -> 22.24909
A109: Delhi | B109: =SUMIFS(Orders!$K$2:$K$1201,Orders!$N$2:$N$1201,$B$7,Orders!$O$2:$O$1201,$B$3,Orders!$Q$2:$Q$1201,$B$5,Orders!$R$2:$R$1201,$B$4,Orders!$T$2:$T$1201,$A109)/$B$6 -> 15.42368 | C109: =B109+ROW()/1000000 -> 15.423789 | F109: 5 | G109: =IF(H109=0,"–",INDEX($A$105:$A$116,MATCH(LARGE($C$105:$C$116,F109),$C$105:$C$116,0))) -> Bhubaneswar | H109: =IF(INDEX($B$105:$B$116,MATCH(LARGE($C$105:$C$116,F109),$C$105:$C$116,0))<=0,0,INDEX($B$105:$B$116,MATCH(LARGE($C$105:$C$116,F109),$C$105:$C$116,0))) -> 19.941025
A110: Gurugram | B110: =SUMIFS(Orders!$K$2:$K$1201,Orders!$N$2:$N$1201,$B$7,Orders!$O$2:$O$1201,$B$3,Orders!$Q$2:$Q$1201,$B$5,Orders!$R$2:$R$1201,$B$4,Orders!$T$2:$T$1201,$A110)/$B$6 -> 24.911685 | C110: =B110+ROW()/1000000 -> 24.911795 | F110: 6 | G110: =IF(H110=0,"–",INDEX($A$105:$A$116,MATCH(LARGE($C$105:$C$116,F110),$C$105:$C$116,0))) -> Kolkata | H110: =IF(INDEX($B$105:$B$116,MATCH(LARGE($C$105:$C$116,F110),$C$105:$C$116,0))<=0,0,INDEX($B$105:$B$116,MATCH(LARGE($C$105:$C$116,F110),$C$105:$C$116,0))) -> 17.010345
A111: Hyderabad | B111: =SUMIFS(Orders!$K$2:$K$1201,Orders!$N$2:$N$1201,$B$7,Orders!$O$2:$O$1201,$B$3,Orders!$Q$2:$Q$1201,$B$5,Orders!$R$2:$R$1201,$B$4,Orders!$T$2:$T$1201,$A111)/$B$6 -> 5.772625 | C111: =B111+ROW()/1000000 -> 5.772736 | F111: 7 | G111: =IF(H111=0,"–",INDEX($A$105:$A$116,MATCH(LARGE($C$105:$C$116,F111),$C$105:$C$116,0))) -> Lucknow | H111: =IF(INDEX($B$105:$B$116,MATCH(LARGE($C$105:$C$116,F111),$C$105:$C$116,0))<=0,0,INDEX($B$105:$B$116,MATCH(LARGE($C$105:$C$116,F111),$C$105:$C$116,0))) -> 15.711115
A112: Jaipur | B112: =SUMIFS(Orders!$K$2:$K$1201,Orders!$N$2:$N$1201,$B$7,Orders!$O$2:$O$1201,$B$3,Orders!$Q$2:$Q$1201,$B$5,Orders!$R$2:$R$1201,$B$4,Orders!$T$2:$T$1201,$A112)/$B$6 -> 30.57814 | C112: =B112+ROW()/1000000 -> 30.578252 | F112: 8 | G112: =IF(H112=0,"–",INDEX($A$105:$A$116,MATCH(LARGE($C$105:$C$116,F112),$C$105:$C$116,0))) -> Delhi | H112: =IF(INDEX($B$105:$B$116,MATCH(LARGE($C$105:$C$116,F112),$C$105:$C$116,0))<=0,0,INDEX($B$105:$B$116,MATCH(LARGE($C$105:$C$116,F112),$C$105:$C$116,0))) -> 15.42368
A113: Kolkata | B113: =SUMIFS(Orders!$K$2:$K$1201,Orders!$N$2:$N$1201,$B$7,Orders!$O$2:$O$1201,$B$3,Orders!$Q$2:$Q$1201,$B$5,Orders!$R$2:$R$1201,$B$4,Orders!$T$2:$T$1201,$A113)/$B$6 -> 17.010345 | C113: =B113+ROW()/1000000 -> 17.010458
A114: Lucknow | B114: =SUMIFS(Orders!$K$2:$K$1201,Orders!$N$2:$N$1201,$B$7,Orders!$O$2:$O$1201,$B$3,Orders!$Q$2:$Q$1201,$B$5,Orders!$R$2:$R$1201,$B$4,Orders!$T$2:$T$1201,$A114)/$B$6 -> 15.711115 | C114: =B114+ROW()/1000000 -> 15.711229
A115: Mumbai | B115: =SUMIFS(Orders!$K$2:$K$1201,Orders!$N$2:$N$1201,$B$7,Orders!$O$2:$O$1201,$B$3,Orders!$Q$2:$Q$1201,$B$5,Orders!$R$2:$R$1201,$B$4,Orders!$T$2:$T$1201,$A115)/$B$6 -> 14.31928 | C115: =B115+ROW()/1000000 -> 14.319395
A116: Pune | B116: =SUMIFS(Orders!$K$2:$K$1201,Orders!$N$2:$N$1201,$B$7,Orders!$O$2:$O$1201,$B$3,Orders!$Q$2:$Q$1201,$B$5,Orders!$R$2:$R$1201,$B$4,Orders!$T$2:$T$1201,$A116)/$B$6 -> 22.24909 | C116: =B116+ROW()/1000000 -> 22.249206
A118: Order status mix (count of orders; respects all filters)
A119: Status | B119: Orders
A120: Delivered | B120: =COUNTIFS(Orders!$N$2:$N$1201,$A120,Orders!$O$2:$O$1201,$B$3,Orders!$Q$2:$Q$1201,$B$5,Orders!$R$2:$R$1201,$B$4) -> 1091
A121: Returned | B121: =COUNTIFS(Orders!$N$2:$N$1201,$A121,Orders!$O$2:$O$1201,$B$3,Orders!$Q$2:$Q$1201,$B$5,Orders!$R$2:$R$1201,$B$4) -> 75
A122: Cancelled | B122: =COUNTIFS(Orders!$N$2:$N$1201,$A122,Orders!$O$2:$O$1201,$B$3,Orders!$Q$2:$Q$1201,$B$5,Orders!$R$2:$R$1201,$B$4) -> 34

Sheet Orders
A1: order_id | B1: order_date | C1: ship_date | D1: customer_id | E1: product_id | F1: sales_channel | G1: payment_method | H1: quantity | I1: unit_price_inr | J1: discount_pct | K1: sales_inr | L1: cost_inr | M1: profit_inr | N1: order_status | O1: order_year | P1: order_month | Q1: category | R1: region | S1: segment | T1: city
A2: O00001 | B2: 45585 | C2: 45587 | D2: C001 | E2: P005 | F2: Phone | G2: Debit Card | H2: 2 | I2: 6500 | J2: 0.15 | K2: 11050 | L2: 8400 | M2: 2650 | N2: Delivered | O2: =YEAR(B2) -> 2024 | P2: =DATE(YEAR(B2),MONTH(B2),1) -> 45566 | Q2: =INDEX(Products!$C$2:$C$16,MATCH(E2,Products!$A$2:$A$16,0)) -> Furniture | R2: =INDEX(Customers!$F$2:$F$101,MATCH(D2,Customers!$A$2:$A$101,0)) -> East | S2: =INDEX(Customers!$C$2:$C$101,MATCH(D2,Customers!$A$2:$A$101,0)) -> Small Business | T2: =INDEX(Customers!$D$2:$D$101,MATCH(D2,Customers!$A$2:$A$101,0)) -> Kolkata
A3: O00002 | B3: 45510 | C3: 45515 | D3: C057 | E3: P011 | F3: Phone | G3: Credit Card | H3: 2 | I3: 2200 | J3: 0.25 | K3: 3300 | L3: 2600 | M3: 700 | N3: Delivered | O3: =YEAR(B3) -> 2024 | P3: =DATE(YEAR(B3),MONTH(B3),1) -> 45505 | Q3: =INDEX(Products!$C$2:$C$16,MATCH(E3,Products!$A$2:$A$16,0)) -> Technology | R3: =INDEX(Customers!$F$2:$F$101,MATCH(D3,Customers!$A$2:$A$101,0)) -> East | S3: =INDEX(Customers!$C$2:$C$101,MATCH(D3,Customers!$A$2:$A$101,0)) -> Consumer | T3: =INDEX(Customers!$D$2:$D$101,MATCH(D3,Customers!$A$2:$A$101,0)) -> Bhubaneswar
A4: O00003 | B4: 45971 | C4: 45977 | D4: C037 | E4: P009 | F4: Online | G4: Debit Card | H4: 3 | I4: 180 | J4: 0 | K4: 540 | L4: 210 | M4: 330 | N4: Delivered | O4: =YEAR(B4) -> 2025 | P4: =DATE(YEAR(B4),MONTH(B4),1) -> 45962 | Q4: =INDEX(Products!$C$2:$C$16,MATCH(E4,Products!$A$2:$A$16,0)) -> Office Supplies | R4: =INDEX(Customers!$F$2:$F$101,MATCH(D4,Customers!$A$2:$A$101,0)) -> North | S4: =INDEX(Customers!$C$2:$C$101,MATCH(D4,Customers!$A$2:$A$101,0)) -> Corporate | T4: =INDEX(Customers!$D$2:$D$101,MATCH(D4,Customers!$A$2:$A$101,0)) -> Jaipur
A5: O00004 | B5: 45317 | C5: 45318 | D5: C026 | E5: P003 | F5: Phone | G5: UPI | H5: 1 | I5: 1500 | J5: 0.1 | K5: 1350 | L5: 850 | M5: 500 | N5: Delivered | O5: =YEAR(B5) -> 2024 | P5: =DATE(YEAR(B5),MONTH(B5),1) -> 45292 | Q5: =INDEX(Products!$C$2:$C$16,MATCH(E5,Products!$A$2:$A$16,0)) -> Technology | R5: =INDEX(Customers!$F$2:$F$101,MATCH(D5,Customers!$A$2:$A$101,0)) -> North | S5: =INDEX(Customers!$C$2:$C$101,MATCH(D5,Customers!$A$2:$A$101,0)) -> Consumer | T5: =INDEX(Customers!$D$2:$D$101,MATCH(D5,Customers!$A$2:$A$101,0)) -> Gurugram
A6: O00005 | B6: 45491 | C6: 45497 | D6: C081 | E6: P010 | F6: Store | G6: Credit Card | H6: 3 | I6: 5500 | J6: 0.1 | K6: 14850 | L6: 11100 | M6: 3750 | N6: Delivered | O6: =YEAR(B6) -> 2024 | P6: =DATE(YEAR(B6),MONTH(B6),1) -> 45474 | Q6: =INDEX(Products!$C$2:$C$16,MATCH(E6,Products!$A$2:$A$16,0)) -> Furniture | R6: =INDEX(Customers!$F$2:$F$101,MATCH(D6,Customers!$A$2:$A$101,0)) -> West | S6: =INDEX(Customers!$C$2:$C$101,MATCH(D6,Customers!$A$2:$A$101,0)) -> Corporate | T6: =INDEX(Customers!$D$2:$D$101,MATCH(D6,Customers!$A$2:$A$101,0)) -> Mumbai
A7: O00006 | B7: 46206 | C7: 46213 | D7: C089 | E7: P001 | F7: Store | G7: Credit Card | H7: 5 | I7: 45000 | J7: 0 | K7: 225000 | L7: 180000 | M7: 45000 | N7: Delivered | O7: =YEAR(B7) -> 2026 | P7: =DATE(YEAR(B7),MONTH(B7),1) -> 46204 | Q7: =INDEX(Products!$C$2:$C$16,MATCH(E7,Products!$A$2:$A$16,0)) -> Technology | R7: =INDEX(Customers!$F$2:$F$101,MATCH(D7,Customers!$A$2:$A$101,0)) -> North | S7: =INDEX(Customers!$C$2:$C$101,MATCH(D7,Customers!$A$2:$A$101,0)) -> Small Business | T7: =INDEX(Customers!$D$2:$D$101,MATCH(D7,Customers!$A$2:$A$101,0)) -> Gurugram
A8: O00007 | B8: 45767 | C8: 45768 | D8: C090 | E8: P009 | F8: Online | G8: Cash | H8: 3 | I8: 180 | J8: 0.25 | K8: 405 | L8: 210 | M8: 195 | N8: Delivered | O8: =YEAR(B8) -> 2025 | P8: =DATE(YEAR(B8),MONTH(B8),1) -> 45748 | Q8: =INDEX(Products!$C$2:$C$16,MATCH(E8,Products!$A$2:$A$16,0)) -> Office Supplies | R8: =INDEX(Customers!$F$2:$F$101,MATCH(D8,Customers!$A$2:$A$101,0)) -> West | S8: =INDEX(Customers!$C$2:$C$101,MATCH(D8,Customers!$A$2:$A$101,0)) -> Consumer | T8: =INDEX(Customers!$D$2:$D$101,MATCH(D8,Customers!$A$2:$A$101,0)) -> Ahmedabad
A9: O00008 | B9: 45835 | C9: 45840 | D9: C060 | E9: P011 | F9: Store | G9: Net Banking | H9: 3 | I9: 2200 | J9: 0.25 | K9: 4950 | L9: 3900 | M9: 1050 | N9: Delivered | O9: =YEAR(B9) -> 2025 | P9: =DATE(YEAR(B9),MONTH(B9),1) -> 45809 | Q9: =INDEX(Products!$C$2:$C$16,MATCH(E9,Products!$A$2:$A$16,0)) -> Technology | R9: =INDEX(Customers!$F$2:$F$101,MATCH(D9,Customers!$A$2:$A$101,0)) -> South | S9: =INDEX(Customers!$C$2:$C$101,MATCH(D9,Customers!$A$2:$A$101,0)) -> Consumer | T9: =INDEX(Customers!$D$2:$D$101,MATCH(D9,Customers!$A$2:$A$101,0)) -> Bengaluru
A10: O00009 | B10: 46142 | C10: 46147 | D10: C065 | E10: P007 | F10: Phone | G10: Cash | H10: 2 | I10: 250 | J10: 0 | K10: 500 | L10: 240 | M10: 260 | N10: Delivered | O10: =YEAR(B10) -> 2026 | P10: =DATE(YEAR(B10),MONTH(B10),1) -> 46113 | Q10: =INDEX(Products!$C$2:$C$16,MATCH(E10,Products!$A$2:$A$16,0)) -> Office Supplies | R10: =INDEX(Customers!$F$2:$F$101,MATCH(D10,Customers!$A$2:$A$101,0)) -> East | S10: =INDEX(Customers!$C$2:$C$101,MATCH(D10,Customers!$A$2:$A$101,0)) -> Corporate | T10: =INDEX(Customers!$D$2:$D$101,MATCH(D10,Customers!$A$2:$A$101,0)) -> Kolkata
A11: O00010 | B11: 46152 | C11: 46158 | D11: C097 | E11: P004 | F11: Phone | G11: Cash | H11: 1 | I11: 12000 | J11: 0.25 | K11: 9000 | L11: 9000 | M11: 0 | N11: Delivered | O11: =YEAR(B11) -> 2026 | P11: =DATE(YEAR(B11),MONTH(B11),1) -> 46143 | Q11: =INDEX(Products!$C$2:$C$16,MATCH(E11,Products!$A$2:$A$16,0)) -> Technology | R11: =INDEX(Customers!$F$2:$F$101,MATCH(D11,Customers!$A$2:$A$101,0)) -> East | S11: =INDEX(Customers!$C$2:$C$101,MATCH(D11,Customers!$A$2:$A$101,0)) -> Small Business | T11: =INDEX(Customers!$D$2:$D$101,MATCH(D11,Customers!$A$2:$A$101,0)) -> Bhubaneswar
A12: O00011 | B12: 45371 | C12: 45377 | D12: C036 | E12: P008 | F12: Store | G12: Debit Card | H12: 1 | I12: 400 | J12: 0.05 | K12: 380 | L12: 260 | M12: 120 | N12: Delivered | O12: =YEAR(B12) -> 2024 | P12: =DATE(YEAR(B12),MONTH(B12),1) -> 45352 | Q12: =INDEX(Products!$C$2:$C$16,MATCH(E12,Products!$A$2:$A$16,0)) -> Office Supplies | R12: =INDEX(Customers!$F$2:$F$101,MATCH(D12,Customers!$A$2:$A$101,0)) -> North | S12: =INDEX(Customers!$C$2:$C$101,MATCH(D12,Customers!$A$2:$A$101,0)) -> Small Business | T12: =INDEX(Customers!$D$2:$D$101,MATCH(D12,Customers!$A$2:$A$101,0)) -> Gurugram
A13: O00012 | B13: 45446 | C13: 45448 | D13: C011 | E13: P003 | F13: Phone | G13: Credit Card | H13: 2 | I13: 1500 | J13: 0 | K13: 3000 | L13: 1700 | M13: 1300 | N13: Delivered | O13: =YEAR(B13) -> 2024 | P13: =DATE(YEAR(B13),MONTH(B13),1) -> 45444 | Q13: =INDEX(Products!$C$2:$C$16,MATCH(E13,Products!$A$2:$A$16,0)) -> Technology | R13: =INDEX(Customers!$F$2:$F$101,MATCH(D13,Customers!$A$2:$A$101,0)) -> South | S13: =INDEX(Customers!$C$2:$C$101,MATCH(D13,Customers!$A$2:$A$101,0)) -> Consumer | T13: =INDEX(Customers!$D$2:$D$101,MATCH(D13,Customers!$A$2:$A$101,0)) -> Chennai
... A1201: O01200 | B1201: 45555 | C1201: 45559 | D1201: C094 | E1201: P003 | F1201: Store | G1201: Cash | H1201: 2 | I1201: 1500 | J1201: 0.1 | K1201: 2700 | L1201: 1700 | M1201: 1000 | N1201: Delivered | O1201: =YEAR(B1201) -> 2024 | P1201: =DATE(YEAR(B1201),MONTH(B1201),1) -> 45536 | Q1201: =INDEX(Products!$C$2:$C$16,MATCH(E1201,Products!$A$2:$A$16,0)) -> Technology | R1201: =INDEX(Customers!$F$2:$F$101,MATCH(D1201,Customers!$A$2:$A$101,0)) -> North | S1201: =INDEX(Customers!$C$2:$C$101,MATCH(D1201,Customers!$A$2:$A$101,0)) -> Small Business | T1201: =INDEX(Customers!$D$2:$D$101,MATCH(D1201,Customers!$A$2:$A$101,0)) -> Lucknow

Sheet Customers
A1: customer_id | B1: customer_name | C1: segment | D1: city | E1: state | F1: region | G1: signup_date
A2: C001 | B2: Arjun Sharma | C2: Small Business | D2: Kolkata | E2: West Bengal | F2: East | G2: 45125
A3: C002 | B3: Aanya Mehta | C3: Small Business | D3: Lucknow | E3: Uttar Pradesh | F3: North | G3: 44771
A4: C003 | B4: Nisha Gupta | C4: Small Business | D4: Kolkata | E4: West Bengal | F4: East | G4: 45426
A5: C004 | B5: Aarav Gupta | C5: Consumer | D5: Delhi | E5: Delhi | F5: North | G5: 45038
A6: C005 | B6: Priya Sharma | C6: Small Business | D6: Chennai | E6: Tamil Nadu | F6: South | G6: 44969
A7: C006 | B7: Nisha Joshi | C7: Consumer | D7: Bhubaneswar | E7: Odisha | F7: East | G7: 45481
A8: C007 | B8: Diya Sharma | C8: Consumer | D8: Hyderabad | E8: Telangana | F8: South | G8: 45427
A9: C008 | B9: Diya Mehta | C9: Consumer | D9: Pune | E9: Maharashtra | F9: West | G9: 45251
A10: C009 | B10: Aditya Iyer | C10: Consumer | D10: Gurugram | E10: Haryana | F10: North | G10: 45297
A11: C010 | B11: Priya Patel | C11: Consumer | D11: Pune | E11: Maharashtra | F11: West | G11: 45502
A12: C011 | B12: Arjun Iyer | C12: Consumer | D12: Chennai | E12: Tamil Nadu | F12: South | G12: 45692
A13: C012 | B13: Priya Jain | C13: Small Business | D13: Mumbai | E13: Maharashtra | F13: West | G13: 44955
... A101: C100 | B101: Rahul Khan | C101: Corporate | D101: Hyderabad | E101: Telangana | F101: South | G101: 45684

Sheet Products
A1: product_id | B1: product_name | C1: category | D1: list_price_inr | E1: unit_cost_inr
A2: P001 | B2: Laptop | C2: Technology | D2: 45000 | E2: 36000
A3: P002 | B3: Wireless Mouse | C3: Technology | D3: 800 | E3: 420
A4: P003 | B4: Keyboard | C4: Technology | D4: 1500 | E4: 850
A5: P004 | B5: Monitor | C5: Technology | D5: 12000 | E5: 9000
A6: P005 | B6: Office Chair | C6: Furniture | D6: 6500 | E6: 4200
A7: P006 | B7: Office Desk | C7: Furniture | D7: 9000 | E7: 6500
A8: P007 | B8: Notebook Pack | C8: Office Supplies | D8: 250 | E8: 120
A9: P008 | B9: Printer Paper | C9: Office Supplies | D9: 400 | E9: 260
A10: P009 | B10: Pen Set | C10: Office Supplies | D10: 180 | E10: 70
A11: P010 | B11: Bookshelf | C11: Furniture | D11: 5500 | E11: 3700
A12: P011 | B12: Headphones | C12: Technology | D12: 2200 | E12: 1300
A13: P012 | B13: Webcam | C13: Technology | D13: 3000 | E13: 1900
... A16: P015 | B16: Tablet | C16: Technology | D16: 18000 | E16: 14000

Sheet Data_Dictionary
A1: column_name | B1: meaning | C1: sheet
A2: order_id | B2: Unique identifier for each order line | C2: Orders
A3: customer_id | B3: Links an order to a customer | C3: Orders and Customers
A4: product_id | B4: Links an order to a product | C4: Orders and Products
A5: sales_inr | B5: Revenue after discount, in Indian rupees | C5: Orders
A6: cost_inr | B6: Estimated cost of goods sold, in Indian rupees | C6: Orders
A7: profit_inr | B7: Sales minus cost, in Indian rupees | C7: Orders
A8: discount_pct | B8: Discount rate stored as a decimal (0.10 = 10%) | C8: Orders
A9: segment | B9: Customer group | C9: Customers
A10: region | B10: Broad geographic region | C10: Customers
A11: category | B11: Product category | C11: Products
